runelite_python/__init__.py
runelite_python/example.py
runelite_python/gather.py
runelite_python/main.py
runelite_python/cli/cli.py
runelite_python/client/__init__.py
runelite_python/client/client.py
runelite_python/collection/__init__.py
runelite_python/collection/npc.py
runelite_python/collection/scene.py
runelite_python/collection/screen.py
runelite_python/config/publisher_config.py
runelite_python/examples/custom_setup.py
runelite_python/java/__init__.py
runelite_python/java/clickqueue.py
runelite_python/java/helpers.py
runelite_python/java/screenshot.py
runelite_python/java/api/__init__.py
runelite_python/java/api/actor.py
runelite_python/java/api/chat_line_buffer.py
runelite_python/java/api/client.py
runelite_python/java/api/enum_manager.py
runelite_python/java/api/gameobject.py
runelite_python/java/api/grandexchange.py
runelite_python/java/api/groundobject.py
runelite_python/java/api/menu.py
runelite_python/java/api/menuentry.py
runelite_python/java/api/message_node.py
runelite_python/java/api/node.py
runelite_python/java/api/npc.py
runelite_python/java/api/player.py
runelite_python/java/api/scene.py
runelite_python/java/api/skill.py
runelite_python/java/api/tile.py
runelite_python/java/api/tileobject.py
runelite_python/java/api/world.py
runelite_python/java/api/world_view.py
runelite_python/java/api/coord/__init__.py
runelite_python/java/api/coord/localpoint.py
runelite_python/java/api/coord/worldpoint.py
runelite_python/java/api/ids/__init__.py
runelite_python/java/api/ids/id.py
runelite_python/java/api/ids/itemid.py
runelite_python/java/api/ids/npcid.py
runelite_python/java/api/ids/nullobjectid.py
runelite_python/java/api/ids/objectid.py
runelite_python/runelite_data/__init__.py
runelite_python/runelite_data/client_pub.py
runelite_python/runelite_data/master_sub.py
runelite_python/runelite_data/message_pub.py
runelite_python/runelite_data/player_pub.py
runelite_python/runelite_data/publisher.py
runelite_python/runelite_data/scene_pub.py
runelite_python-0.0.2.dist-info/METADATA
runelite_python-0.0.2.dist-info/WHEEL
runelite_python-0.0.2.dist-info/RECORD
